manimxyzmove/__init__.py
manimxyzmove/xyzmove.py
manimxyzmove-0.0.4.dist-info/METADATA
manimxyzmove-0.0.4.dist-info/WHEEL
manimxyzmove-0.0.4.dist-info/licenses/LICENCE
manimxyzmove-0.0.4.dist-info/RECORD
