Metadata-Version: 2.3
Name: manimxyzmove
Version: 0.0.4
Summary: Utitlity to move along an (x,y,z) defined path in manim.
Author-email: iHnR <ihnr@proton.me>
Classifier: License :: OSI Approved :: MIT License
Classifier: Operating System :: OS Independent
Classifier: Programming Language :: Python :: 3
Requires-Python: >=3.8
Requires-Dist: manim
Requires-Dist: numpy
